odoo/addons/purchase_order_line_packaging_qty/README.rst
odoo/addons/purchase_order_line_packaging_qty/__init__.py
odoo/addons/purchase_order_line_packaging_qty/__manifest__.py
odoo/addons/purchase_order_line_packaging_qty/i18n/purchase_order_line_packaging_qty.pot
odoo/addons/purchase_order_line_packaging_qty/models/__init__.py
odoo/addons/purchase_order_line_packaging_qty/models/purchase_order_line.py
odoo/addons/purchase_order_line_packaging_qty/readme/CONTRIBUTORS.rst
odoo/addons/purchase_order_line_packaging_qty/readme/DESCRIPTION.rst
odoo/addons/purchase_order_line_packaging_qty/static/description/icon.png
odoo/addons/purchase_order_line_packaging_qty/static/description/index.html
odoo/addons/purchase_order_line_packaging_qty/tests/__init__.py
odoo/addons/purchase_order_line_packaging_qty/tests/test_purchase_order_line_packaging_qty.py
odoo/addons/purchase_order_line_packaging_qty/views/purchase_order.xml
odoo14_addon_purchase_order_line_packaging_qty-14.0.1.0.1.dist-info/METADATA
odoo14_addon_purchase_order_line_packaging_qty-14.0.1.0.1.dist-info/WHEEL
odoo14_addon_purchase_order_line_packaging_qty-14.0.1.0.1.dist-info/top_level.txt
odoo14_addon_purchase_order_line_packaging_qty-14.0.1.0.1.dist-info/RECORD
